pykiq/__init__.py
pykiq/base.py
pykiq/connector.py
pykiq/error.py
pykiq/job.py
pykiq/protocol.py
pykiq/sidekiq.py
pykiq-0.10.3.dist-info/LICENSE
pykiq-0.10.3.dist-info/METADATA
pykiq-0.10.3.dist-info/WHEEL
pykiq-0.10.3.dist-info/top_level.txt
pykiq-0.10.3.dist-info/RECORD
