Metadata-Version: 2.1
Name: pykiq
Version: 0.10.3
Summary: A simple storage system for dataclasses.
Home-page: https://github.com/carstencodes/dcstore
Author: Carsten Igel
Author-email: cig@bite-that-bit.de
License: LGPL-3.0-only
Keywords: sidekiq,job,development
Platform: UNKNOWN
Classifier: Development Status :: 4 - Beta
Classifier: Intended Audience :: Developers
Classifier: License :: OSI Approved :: GNU Lesser General Public License v3 (LGPLv3)
Classifier: Operating System :: OS Independent
Classifier: Programming Language :: Python :: 3.8
Classifier: Programming Language :: Python :: 3.9
Classifier: Topic :: System :: Networking
Classifier: Topic :: System :: Systems Administration
Classifier: Topic :: Software Development :: Libraries :: Python Modules
Classifier: Topic :: System
Classifier: Typing :: Typed
Requires-Python: >=3.7, < 4
Requires-Dist: redis
